petromap/__init__.py
petromap/essentials.py
petromap-0.1.53.dist-info/METADATA
petromap-0.1.53.dist-info/WHEEL
petromap-0.1.53.dist-info/top_level.txt
petromap-0.1.53.dist-info/RECORD
