Metadata-Version: 2.4
Name: PetroMap
Version: 0.1.53
Summary: A GeoSpatial Contouring Mapping Utility for Oil and Gas Engineers
Home-page: https://github.com/Nashat90/
Author: Nashat Jumaah Omar
Classifier: Programming Language :: Python :: 3
Classifier: License :: OSI Approved :: MIT License
Classifier: Operating System :: OS Independent
Requires-Python: >=3.8
Requires-Dist: matplotlib
Requires-Dist: scipy
Requires-Dist: plotly
Requires-Dist: scikit-learn
Requires-Dist: pykrige
Dynamic: author
Dynamic: classifier
Dynamic: description
Dynamic: description-content-type
Dynamic: home-page
Dynamic: requires-dist
Dynamic: requires-python
Dynamic: summary
